{
    "api": {
        "zuraaa": {
            "url": "https://zuraaa.com/api/",
            "secret": ""
        }
    },
    "bot": {
        "token": "BotToken",
        "prefix": "Prefix",
        "owner": [
            "OwnerID (WIP)"
        ],
        "primaryColor": "cor para as embeds",
        "guilds": {
            "main": {
                "id": "guild",
                "autorole": {
                    "botrole": "bot role",
                    "member": "member role",
                    "dev": "developer role"
                },
                "channels": {
                    "welcome": "canal de boas vindas",
                    "modlog": "canal de mod logs",
                    "sitelog": "canal de site logs",
                    "upDownChannels": [
                        "canal de sugestões",
                        "outros canais com essa feature"
                    ],
                    "starboard": "starboard channel",
                    "formlog": "form logs channel",
                    "forms": "forms channel"
                },
                "staffroleid": {
                    "mod": "mod role",
                    "adm": "adm role",
                    "checker": "checker role"
                },
                "otherroles": {
                    "mute": "mute role",
                    "topbots": "top_bots role",
                    "topbotdevs": "top_devs role"
                }
            },
            "bottest": {
                "id": "id do servidor que os bots são testados",
                "autorole": {
                    "botrole": "bot role"
                }
            }
        }
    },
    "rabbit": {
      "url": "amqp://localhost"
    }
}
